<?xml version="1.0" encoding="UTF-8"?>
<ti:work xmlns:ti="http://chs.harvard.edu/xmlns/cts" groupUrn="urn:cts:greekLit:tlg1389" projid="greekLit:tlg001" urn="urn:cts:greekLit:tlg1389.tlg001" xml:lang="grc">   
   <ti:title xml:lang="lat">Lexicon in decem oratores Atticos</ti:title>    
   <ti:edition projid="greekLit:perseus-grc2" workUrn="urn:cts:greekLit:tlg1389.tlg001" urn="urn:cts:greekLit:tlg1389.tlg001.perseus-grc2" xml:lang="grc">        
      <ti:label xml:lang="lat">Lexicon in decem oratores Atticos</ti:label>
      <ti:description xml:lang="mul">Harpocration, Valerius. Harpocrationis Lexicon in decem oratores Atticos. Dindorf, Wilhelm, editor. Oxford: E Typographeo Academico, 1853.</ti:description>
   </ti:edition> 
</ti:work>

