<?xml version="1.0" encoding="UTF-8"?>
<ti:work xmlns:ti="http://chs.harvard.edu/xmlns/cts" groupUrn="urn:cts:greekLit:tlg0014" projid="greekLit:tlg037" urn="urn:cts:greekLit:tlg0014.tlg037" xml:lang="grc">
    
   <ti:title xml:lang="eng">Against Pantaenetus</ti:title>
   
   <ti:edition urn="urn:cts:greekLit:tlg0014.tlg037.perseus-grc2" workUrn="urn:cts:greekLit:tlg0014.tlg037" xml:lang="grc">
      <ti:label xml:lang="grc">παραγραφὴ πρὸς Πανταίνετον</ti:label>
      <ti:description xml:lang="mul">Demosthenis. Orationes. Vol. 2, Part 2. Rennie, W., editor. Oxford: Clarendon Press, 1921.</ti:description>
   </ti:edition> 
   
   <ti:translation urn="urn:cts:greekLit:tlg0014.tlg037.perseus-eng2" workUrn="urn:cts:greekLit:tlg0014.tlg037" xml:lang="eng">
      <ti:label xml:lang="eng">Nicobulus Against Pantaenetus</ti:label>
      <ti:description xml:lang="eng">Demosthenes. Vol. IV. Orations, XXVII-XL. Murray, A. T., translator. Cambridge, MA: Harvard University Press, 1936 (printing).</ti:description>
   </ti:translation>

</ti:work>
