<?xml version="1.0" encoding="UTF-8"?>
<ti:work xmlns:ti="http://chs.harvard.edu/xmlns/cts" groupUrn="urn:cts:greekLit:tlg0032" projid="greekLit:tlg003" urn="urn:cts:greekLit:tlg0032.tlg003" xml:lang="grc">
            
   <ti:title xml:lang="eng">Economics</ti:title>  
   <ti:title xml:lang="lat">Oeconomicus</ti:title>
   <ti:title xml:lang="grc">Οἰκονομικός</ti:title>
   
      
      <ti:edition urn="urn:cts:greekLit:tlg0032.tlg003.perseus-grc2" workUrn="urn:cts:greekLit:tlg0032.tlg003">
         <ti:label xml:lang="eng">Economics</ti:label>
         <ti:description xml:lang="eng">Xenophontis Opera omnia Volume II Oeconomicus, Convivium, Apologia SocratisXenophon, creator; Marchant, E. C. (Edgar Cardew), 1864-1960, editor</ti:description>
      </ti:edition>
  
   
   
        
</ti:work>