<?xml version="1.0" encoding="UTF-8"?>
<ti:work xmlns:ti="http://chs.harvard.edu/xmlns/cts" groupUrn="urn:cts:greekLit:tlg0007" projid="greekLit:tlg092" urn="urn:cts:greekLit:tlg0007.tlg092" xml:lang="grc">
    <ti:title xml:lang="lat">De Defectu Oraculorum</ti:title>
    
    <ti:translation urn="urn:cts:greekLit:tlg0007.tlg092.perseus-eng3" workUrn="urn:cts:greekLit:tlg0007.tlg092" xml:lang="eng">
        <ti:label xml:lang="eng">The Obsolesence of Oracles</ti:label>
        <ti:description xml:lang="mul">Plutarch. Moralia, Vol. V. Babbitt, Frank Cole, translator. Cambridge, MA: Harvard University Press. London: William Heinemann Ltd. 1936 (printing).</ti:description>
    </ti:translation>
    
    <ti:translation urn="urn:cts:greekLit:tlg0007.tlg092.perseus-eng4" workUrn="urn:cts:greekLit:tlg0007.tlg092" xml:lang="eng">
        <ti:label xml:lang="eng">Why the Oracles Cease to Give Answers</ti:label>
        <ti:description xml:lang="eng">Plutarch. Plutarch's Morals, Vol. IV. Goodwin, William W., editor; Midgley, Robert translator. Boston: Little, Brown, and Company. Cambridge. 1874.</ti:description>
    </ti:translation>
    
    <ti:edition urn="urn:cts:greekLit:tlg0007.tlg092.perseus-grc2" workUrn="urn:cts:greekLit:tlg0007.tlg092" xml:lang="grc">
        <ti:label xml:lang="grc">Περὶ τῶν ἐκλελοιπότων</ti:label>
        <ti:description xml:lang="mul">Plutarch. Plutarchi Chaeronensis Moralia, Vol IΙI. Vernardakēs, Grēgorios N., editor. 
            Leipzig: Teubner. 1891.</ti:description>
    </ti:edition>
</ti:work>

