<?xml version="1.0" encoding="UTF-8"?>
<ti:work xmlns:ti="http://chs.harvard.edu/xmlns/cts" groupUrn="urn:cts:greekLit:tlg0081" projid="greekLit:tlg002" urn="urn:cts:greekLit:tlg0081.tlg002" xml:lang="grc">
            
   <ti:title xml:lang="lat">De antiquis oratoribus</ti:title>
   
   <ti:edition urn="urn:cts:greekLit:tlg0081.tlg002.perseus-grc2" workUrn="urn:cts:greekLit:tlg0081.tlg002" xml:lang="grc">
      <ti:label xml:lang="grc">Περὶ τῶν ἀρχαίων ῥητόρων</ti:label>
      <ti:description xml:lang="mul">Dionysius of Halicarnassus. Dionysii Halicarnasei Opuscula, Vol 1. Usener, Hermann; Radermacher, Ludwig, editors. Leipzig: Teubner, 1899.</ti:description></ti:edition>
   
</ti:work>