<?xml version="1.0" encoding="UTF-8"?>
<ti:work xmlns:ti="http://chs.harvard.edu/xmlns/cts" groupUrn="urn:cts:greekLit:tlg0019" projid="greekLit:tlg009" urn="urn:cts:greekLit:tlg0019.tlg009" xml:lang="grc">
      
   <ti:title xml:lang="eng">Frogs</ti:title>
    
    <ti:edition urn="urn:cts:greekLit:tlg0019.tlg009.perseus-grc2" workUrn="urn:cts:greekLit:tlg0019.tlg009" xml:lang="grc">
        <ti:label xml:lang="eng">Frogs</ti:label>
        <ti:description xml:lang="eng">Aristophanes. Aristophanes Comoediae, ed. F.W. Hall and W.M. Geldart, vol. 2. Oxford, Clarendon Press, 1907.</ti:description>
    </ti:edition>
      
   <!--<ti:translation projid="greekLit:perseus-eng1" urn="urn:cts:greekLit:tlg0019.tlg009.perseus-eng1" workUrn="urn:cts:greekLit:tlg0019.tlg009">
        
      <ti:label xml:lang="eng">Frogs (English translation by Matthew Dillon)</ti:label>
        
      <ti:description xml:lang="eng"> Aristophanes. Frogs. trans. M. Dillon. Routledge, London; New
          York. 1994.</ti:description>
        
      <ti:memberof collection="Perseus:collection:Greco-Roman-protected"/>
      
   </ti:translation>-->
    
</ti:work>